LICENSE
MANIFEST.in
README.md
setup.py
bin/gittalk
gittalk/__init__.py
gittalk/core.py
gittalk.egg-info/PKG-INFO
gittalk.egg-info/SOURCES.txt
gittalk.egg-info/dependency_links.txt
gittalk.egg-info/not-zip-safe
gittalk.egg-info/requires.txt
gittalk.egg-info/top_level.txt