Metadata-Version: 1.1
Name: gittalk
Version: 0.1.0
Summary: talk with git
Home-page: https://github.com/kqdtran/gittalk
Author: Khoa Tran
Author-email: khoatran@berkeley.edu
License: MIT
Keywords: git,audio,gittalk
Platform: UNKNOWN
Classifier: Development Status :: 3 - Alpha
Classifier: Intended Audience :: Developers
Classifier: Environment :: Console
Classifier: Operating System :: Unix
Classifier: Programming Language :: Python :: 2
